{
  "samedi.json": 113,
  "envato.json": 9138,
  "racket.json": 428,
  "salesforce.json": 1115,
  "localitylabs.json": 0,
  "liquidware.json": 449,
  "acknet.json": 3,
  "latimes.json": 335,
  "platform45.json": 879,
  "vim-ruby.json": 75,
  "xsf.json": 195,
  "kete.json": 445,
  "cohesive.json": 379,
  "lucidnz.json": 325,
  "vokle.json": 211,
  "php.json": 749,
  "cappuccino.json": 4,
  "copypastel.json": 0,
  "researchpath.json": 0,
  "mangos.json": 104,
  "lightserve.json": 0,
  "regroup.json": 17,
  "yeebase.json": 17,
  "doppler.json": 0,
  "ndwebgroup.json": 0,
  "spip.json": 0,
  "mailprotector.json": 73,
  "fastpencil.json": 447,
  "flywheelnetworks.json": 3,
  "openhood.json": 380,
  "webfirm.json": 0,
  "wisemonks.json": 0,
  "shopsavvy.json": 0,
  "gotime.json": 0,
  "elevatedrails.json": 20,
  "radiant.json": 106,
  "aupeo.json": 0,
  "thewinespies.json": 57,
  "cdd.json": 1277,
  "spanner.json": 1132,
  "gnip.json": 156,
  "10gen.json": 212,
  "katalyst.json": 373,
  "99designs.json": 1565,
  "ushahidi.json": 621,
  "resolve.json": 2176,
  "a2c.json": 5,
  "fs.json": 1345,
  "Kadaza.json": 0,
  "handlino.json": 156,
  "lrug.json": 45,
  "sproutventure.json": 6,
  "pixels-and-bits.json": 104,
  "pluginaweek.json": 25,
  "thinkcreate.json": 58,
  "nosco.json": 283,
  "cogenda.json": 89,
  "opensourcerails.json": 19,
  "git.json": 697,
  "Khan.json": 11133,
  "simplificator.json": 682,
  "ging.json": 1050,
  "trisignia.json": 153,
  "twitter4r.json": 0,
  "reddit.json": 2118,
  "codemonkeylabs.json": 1,
  "uken.json": 829,
  "myminderz.json": 0,
  "eet-nu.json": 0,
  "pac.json": 1710,
  "defensio.json": 34,
  "yahoo.json": 945,
  "loadsys.json": 64,
  "translateorgza.json": 0
}
