[{"id": 22348441, "node_id": "MDEwOlJlcG9zaXRvcnkyMjM0ODQ0MQ==", "name": "laptop", "full_name": "clickhere/laptop", "private": false, "owner": {"login": "clickhere", "id": 18863, "node_id": "MDEyOk9yZ2FuaXphdGlvbjE4ODYz", "avatar_url": "https://avatars.githubusercontent.com/u/18863?v=4", "gravatar_id": "", "url": "https://api.github.com/users/clickhere", "html_url": "https://github.com/clickhere", "followers_url": "https://api.github.com/users/clickhere/followers", "following_url": "https://api.github.com/users/clickhere/following{/other_user}", "gists_url": "https://api.github.com/users/clickhere/gists{/gist_id}", "starred_url": "https://api.github.com/users/clickhere/starred{/owner}{/repo}", "subscriptions_url": "https://api.github.com/users/clickhere/subscriptions", "organizations_url": "https://api.github.com/users/clickhere/orgs", "repos_url": "https://api.github.com/users/clickhere/repos", "events_url": "https://api.github.com/users/clickhere/events{/privacy}", "received_events_url": "https://api.github.com/users/clickhere/received_events", "type": "Organization", "site_admin": false}, "html_url": "https://github.com/clickhere/laptop", "description": "Script to setup a laptop for development", "fork": false, "url": "https://api.github.com/repos/clickhere/laptop", "forks_url": "https://api.github.com/repos/clickhere/laptop/forks", "keys_url": "https://api.github.com/repos/clickhere/laptop/keys{/key_id}", "collaborators_url": "https://api.github.com/repos/clickhere/laptop/collaborators{/collaborator}", "teams_url": "https://api.github.com/repos/clickhere/laptop/teams", "hooks_url": "https://api.github.com/repos/clickhere/laptop/hooks", "issue_events_url": "https://api.github.com/repos/clickhere/laptop/issues/events{/number}", "events_url": "https://api.github.com/repos/clickhere/laptop/events", "assignees_url": "https://api.github.com/repos/clickhere/laptop/assignees{/user}", "branches_url": "https://api.github.com/repos/clickhere/laptop/branches{/branch}", "tags_url": "https://api.github.com/repos/clickhere/laptop/tags", "blobs_url": "https://api.github.com/repos/clickhere/laptop/git/blobs{/sha}", "git_tags_url": "https://api.github.com/repos/clickhere/laptop/git/tags{/sha}", "git_refs_url": "https://api.github.com/repos/clickhere/laptop/git/refs{/sha}", "trees_url": "https://api.github.com/repos/clickhere/laptop/git/trees{/sha}", "statuses_url": "https://api.github.com/repos/clickhere/laptop/statuses/{sha}", "languages_url": "https://api.github.com/repos/clickhere/laptop/languages", "stargazers_url": "https://api.github.com/repos/clickhere/laptop/stargazers", "contributors_url": "https://api.github.com/repos/clickhere/laptop/contributors", "subscribers_url": "https://api.github.com/repos/clickhere/laptop/subscribers", "subscription_url": "https://api.github.com/repos/clickhere/laptop/subscription", "commits_url": "https://api.github.com/repos/clickhere/laptop/commits{/sha}", "git_commits_url": "https://api.github.com/repos/clickhere/laptop/git/commits{/sha}", "comments_url": "https://api.github.com/repos/clickhere/laptop/comments{/number}", "issue_comment_url": "https://api.github.com/repos/clickhere/laptop/issues/comments{/number}", "contents_url": "https://api.github.com/repos/clickhere/laptop/contents/{+path}", "compare_url": "https://api.github.com/repos/clickhere/laptop/compare/{base}...{head}", "merges_url": "https://api.github.com/repos/clickhere/laptop/merges", "archive_url": "https://api.github.com/repos/clickhere/laptop/{archive_format}{/ref}", "downloads_url": "https://api.github.com/repos/clickhere/laptop/downloads", "issues_url": "https://api.github.com/repos/clickhere/laptop/issues{/number}", "pulls_url": "https://api.github.com/repos/clickhere/laptop/pulls{/number}", "milestones_url": "https://api.github.com/repos/clickhere/laptop/milestones{/number}", "notifications_url": "https://api.github.com/repos/clickhere/laptop/notifications{?since,all,participating}", "labels_url": "https://api.github.com/repos/clickhere/laptop/labels{/name}", "releases_url": "https://api.github.com/repos/clickhere/laptop/releases{/id}", "deployments_url": "https://api.github.com/repos/clickhere/laptop/deployments", "created_at": "2014-07-28T15:51:44Z", "updated_at": "2019-07-11T17:05:59Z", "pushed_at": "2014-08-08T14:24:05Z", "git_url": "git://github.com/clickhere/laptop.git", "ssh_url": "git@github.com:clickhere/laptop.git", "clone_url": "https://github.com/clickhere/laptop.git", "svn_url": "https://github.com/clickhere/laptop", "homepage": null, "size": 240, "stargazers_count": 1, "watchers_count": 1, "language": "Shell", "has_issues": true, "has_projects": true, "has_downloads": true, "has_wiki": true, "has_pages": false, "forks_count": 0, "mirror_url": null, "archived": false, "disabled": false, "open_issues_count": 0, "license": null, "allow_forking": true, "is_template": false, "web_commit_signoff_required": false, "topics": [], "visibility": "public", "forks": 0, "open_issues": 0, "watchers": 1, "default_branch": "master", "permissions": {"admin": false, "maintain": false, "push": false, "triage": false, "pull": true}}, {"id": 22518652, "node_id": "MDEwOlJlcG9zaXRvcnkyMjUxODY1Mg==", "name": "testjs", "full_name": "clickhere/testjs", "private": false, "owner": {"login": "clickhere", "id": 18863, "node_id": "MDEyOk9yZ2FuaXphdGlvbjE4ODYz", "avatar_url": "https://avatars.githubusercontent.com/u/18863?v=4", "gravatar_id": "", "url": "https://api.github.com/users/clickhere", "html_url": "https://github.com/clickhere", "followers_url": "https://api.github.com/users/clickhere/followers", "following_url": "https://api.github.com/users/clickhere/following{/other_user}", "gists_url": "https://api.github.com/users/clickhere/gists{/gist_id}", "starred_url": "https://api.github.com/users/clickhere/starred{/owner}{/repo}", "subscriptions_url": "https://api.github.com/users/clickhere/subscriptions", "organizations_url": "https://api.github.com/users/clickhere/orgs", "repos_url": "https://api.github.com/users/clickhere/repos", "events_url": "https://api.github.com/users/clickhere/events{/privacy}", "received_events_url": "https://api.github.com/users/clickhere/received_events", "type": "Organization", "site_admin": false}, "html_url": "https://github.com/clickhere/testjs", "description": null, "fork": false, "url": "https://api.github.com/repos/clickhere/testjs", "forks_url": "https://api.github.com/repos/clickhere/testjs/forks", "keys_url": "https://api.github.com/repos/clickhere/testjs/keys{/key_id}", "collaborators_url": "https://api.github.com/repos/clickhere/testjs/collaborators{/collaborator}", "teams_url": "https://api.github.com/repos/clickhere/testjs/teams", "hooks_url": "https://api.github.com/repos/clickhere/testjs/hooks", "issue_events_url": "https://api.github.com/repos/clickhere/testjs/issues/events{/number}", "events_url": "https://api.github.com/repos/clickhere/testjs/events", "assignees_url": "https://api.github.com/repos/clickhere/testjs/assignees{/user}", "branches_url": "https://api.github.com/repos/clickhere/testjs/branches{/branch}", "tags_url": "https://api.github.com/repos/clickhere/testjs/tags", "blobs_url": "https://api.github.com/repos/clickhere/testjs/git/blobs{/sha}", "git_tags_url": "https://api.github.com/repos/clickhere/testjs/git/tags{/sha}", "git_refs_url": "https://api.github.com/repos/clickhere/testjs/git/refs{/sha}", "trees_url": "https://api.github.com/repos/clickhere/testjs/git/trees{/sha}", "statuses_url": "https://api.github.com/repos/clickhere/testjs/statuses/{sha}", "languages_url": "https://api.github.com/repos/clickhere/testjs/languages", "stargazers_url": "https://api.github.com/repos/clickhere/testjs/stargazers", "contributors_url": "https://api.github.com/repos/clickhere/testjs/contributors", "subscribers_url": "https://api.github.com/repos/clickhere/testjs/subscribers", "subscription_url": "https://api.github.com/repos/clickhere/testjs/subscription", "commits_url": "https://api.github.com/repos/clickhere/testjs/commits{/sha}", "git_commits_url": "https://api.github.com/repos/clickhere/testjs/git/commits{/sha}", "comments_url": "https://api.github.com/repos/clickhere/testjs/comments{/number}", "issue_comment_url": "https://api.github.com/repos/clickhere/testjs/issues/comments{/number}", "contents_url": "https://api.github.com/repos/clickhere/testjs/contents/{+path}", "compare_url": "https://api.github.com/repos/clickhere/testjs/compare/{base}...{head}", "merges_url": "https://api.github.com/repos/clickhere/testjs/merges", "archive_url": "https://api.github.com/repos/clickhere/testjs/{archive_format}{/ref}", "downloads_url": "https://api.github.com/repos/clickhere/testjs/downloads", "issues_url": "https://api.github.com/repos/clickhere/testjs/issues{/number}", "pulls_url": "https://api.github.com/repos/clickhere/testjs/pulls{/number}", "milestones_url": "https://api.github.com/repos/clickhere/testjs/milestones{/number}", "notifications_url": "https://api.github.com/repos/clickhere/testjs/notifications{?since,all,participating}", "labels_url": "https://api.github.com/repos/clickhere/testjs/labels{/name}", "releases_url": "https://api.github.com/repos/clickhere/testjs/releases{/id}", "deployments_url": "https://api.github.com/repos/clickhere/testjs/deployments", "created_at": "2014-08-01T16:49:33Z", "updated_at": "2014-08-01T16:49:33Z", "pushed_at": "2014-08-01T16:49:55Z", "git_url": "git://github.com/clickhere/testjs.git", "ssh_url": "git@github.com:clickhere/testjs.git", "clone_url": "https://github.com/clickhere/testjs.git", "svn_url": "https://github.com/clickhere/testjs", "homepage": null, "size": 124, "stargazers_count": 0, "watchers_count": 0, "language": null, "has_issues": true, "has_projects": true, "has_downloads": true, "has_wiki": true, "has_pages": false, "forks_count": 0, "mirror_url": null, "archived": false, "disabled": false, "open_issues_count": 0, "license": null, "allow_forking": true, "is_template": false, "web_commit_signoff_required": false, "topics": [], "visibility": "public", "forks": 0, "open_issues": 0, "watchers": 0, "default_branch": "master", "permissions": {"admin": false, "maintain": false, "push": false, "triage": false, "pull": true}}, {"id": 22524341, "node_id": "MDEwOlJlcG9zaXRvcnkyMjUyNDM0MQ==", "name": "animationjs", "full_name": "clickhere/animationjs", "private": false, "owner": {"login": "clickhere", "id": 18863, "node_id": "MDEyOk9yZ2FuaXphdGlvbjE4ODYz", "avatar_url": "https://avatars.githubusercontent.com/u/18863?v=4", "gravatar_id": "", "url": "https://api.github.com/users/clickhere", "html_url": "https://github.com/clickhere", "followers_url": "https://api.github.com/users/clickhere/followers", "following_url": "https://api.github.com/users/clickhere/following{/other_user}", "gists_url": "https://api.github.com/users/clickhere/gists{/gist_id}", "starred_url": "https://api.github.com/users/clickhere/starred{/owner}{/repo}", "subscriptions_url": "https://api.github.com/users/clickhere/subscriptions", "organizations_url": "https://api.github.com/users/clickhere/orgs", "repos_url": "https://api.github.com/users/clickhere/repos", "events_url": "https://api.github.com/users/clickhere/events{/privacy}", "received_events_url": "https://api.github.com/users/clickhere/received_events", "type": "Organization", "site_admin": false}, "html_url": "https://github.com/clickhere/animationjs", "description": null, "fork": false, "url": "https://api.github.com/repos/clickhere/animationjs", "forks_url": "https://api.github.com/repos/clickhere/animationjs/forks", "keys_url": "https://api.github.com/repos/clickhere/animationjs/keys{/key_id}", "collaborators_url": "https://api.github.com/repos/clickhere/animationjs/collaborators{/collaborator}", "teams_url": "https://api.github.com/repos/clickhere/animationjs/teams", "hooks_url": "https://api.github.com/repos/clickhere/animationjs/hooks", "issue_events_url": "https://api.github.com/repos/clickhere/animationjs/issues/events{/number}", "events_url": "https://api.github.com/repos/clickhere/animationjs/events", "assignees_url": "https://api.github.com/repos/clickhere/animationjs/assignees{/user}", "branches_url": "https://api.github.com/repos/clickhere/animationjs/branches{/branch}", "tags_url": "https://api.github.com/repos/clickhere/animationjs/tags", "blobs_url": "https://api.github.com/repos/clickhere/animationjs/git/blobs{/sha}", "git_tags_url": "https://api.github.com/repos/clickhere/animationjs/git/tags{/sha}", "git_refs_url": "https://api.github.com/repos/clickhere/animationjs/git/refs{/sha}", "trees_url": "https://api.github.com/repos/clickhere/animationjs/git/trees{/sha}", "statuses_url": "https://api.github.com/repos/clickhere/animationjs/statuses/{sha}", "languages_url": "https://api.github.com/repos/clickhere/animationjs/languages", "stargazers_url": "https://api.github.com/repos/clickhere/animationjs/stargazers", "contributors_url": "https://api.github.com/repos/clickhere/animationjs/contributors", "subscribers_url": "https://api.github.com/repos/clickhere/animationjs/subscribers", "subscription_url": "https://api.github.com/repos/clickhere/animationjs/subscription", "commits_url": "https://api.github.com/repos/clickhere/animationjs/commits{/sha}", "git_commits_url": "https://api.github.com/repos/clickhere/animationjs/git/commits{/sha}", "comments_url": "https://api.github.com/repos/clickhere/animationjs/comments{/number}", "issue_comment_url": "https://api.github.com/repos/clickhere/animationjs/issues/comments{/number}", "contents_url": "https://api.github.com/repos/clickhere/animationjs/contents/{+path}", "compare_url": "https://api.github.com/repos/clickhere/animationjs/compare/{base}...{head}", "merges_url": "https://api.github.com/repos/clickhere/animationjs/merges", "archive_url": "https://api.github.com/repos/clickhere/animationjs/{archive_format}{/ref}", "downloads_url": "https://api.github.com/repos/clickhere/animationjs/downloads", "issues_url": "https://api.github.com/repos/clickhere/animationjs/issues{/number}", "pulls_url": "https://api.github.com/repos/clickhere/animationjs/pulls{/number}", "milestones_url": "https://api.github.com/repos/clickhere/animationjs/milestones{/number}", "notifications_url": "https://api.github.com/repos/clickhere/animationjs/notifications{?since,all,participating}", "labels_url": "https://api.github.com/repos/clickhere/animationjs/labels{/name}", "releases_url": "https://api.github.com/repos/clickhere/animationjs/releases{/id}", "deployments_url": "https://api.github.com/repos/clickhere/animationjs/deployments", "created_at": "2014-08-01T19:13:23Z", "updated_at": "2014-08-01T19:13:23Z", "pushed_at": "2014-08-01T19:21:04Z", "git_url": "git://github.com/clickhere/animationjs.git", "ssh_url": "git@github.com:clickhere/animationjs.git", "clone_url": "https://github.com/clickhere/animationjs.git", "svn_url": "https://github.com/clickhere/animationjs", "homepage": null, "size": 184, "stargazers_count": 0, "watchers_count": 0, "language": null, "has_issues": true, "has_projects": true, "has_downloads": true, "has_wiki": true, "has_pages": false, "forks_count": 0, "mirror_url": null, "archived": false, "disabled": false, "open_issues_count": 0, "license": null, "allow_forking": true, "is_template": false, "web_commit_signoff_required": false, "topics": [], "visibility": "public", "forks": 0, "open_issues": 0, "watchers": 0, "default_branch": "master", "permissions": {"admin": false, "maintain": false, "push": false, "triage": false, "pull": true}}, {"id": 49237266, "node_id": "MDEwOlJlcG9zaXRvcnk0OTIzNzI2Ng==", "name": "zf-content-negotiation", "full_name": "clickhere/zf-content-negotiation", "private": false, "owner": {"login": "clickhere", "id": 18863, "node_id": "MDEyOk9yZ2FuaXphdGlvbjE4ODYz", "avatar_url": "https://avatars.githubusercontent.com/u/18863?v=4", "gravatar_id": "", "url": "https://api.github.com/users/clickhere", "html_url": "https://github.com/clickhere", "followers_url": "https://api.github.com/users/clickhere/followers", "following_url": "https://api.github.com/users/clickhere/following{/other_user}", "gists_url": "https://api.github.com/users/clickhere/gists{/gist_id}", "starred_url": "https://api.github.com/users/clickhere/starred{/owner}{/repo}", "subscriptions_url": "https://api.github.com/users/clickhere/subscriptions", "organizations_url": "https://api.github.com/users/clickhere/orgs", "repos_url": "https://api.github.com/users/clickhere/repos", "events_url": "https://api.github.com/users/clickhere/events{/privacy}", "received_events_url": "https://api.github.com/users/clickhere/received_events", "type": "Organization", "site_admin": false}, "html_url": "https://github.com/clickhere/zf-content-negotiation", "description": null, "fork": true, "url": "https://api.github.com/repos/clickhere/zf-content-negotiation", "forks_url": "https://api.github.com/repos/clickhere/zf-content-negotiation/forks", "keys_url": "https://api.github.com/repos/clickhere/zf-content-negotiation/keys{/key_id}", "collaborators_url": "https://api.github.com/repos/clickhere/zf-content-negotiation/collaborators{/collaborator}", "teams_url": "https://api.github.com/repos/clickhere/zf-content-negotiation/teams", "hooks_url": "https://api.github.com/repos/clickhere/zf-content-negotiation/hooks", "issue_events_url": "https://api.github.com/repos/clickhere/zf-content-negotiation/issues/events{/number}", "events_url": "https://api.github.com/repos/clickhere/zf-content-negotiation/events", "assignees_url": "https://api.github.com/repos/clickhere/zf-content-negotiation/assignees{/user}", "branches_url": "https://api.github.com/repos/clickhere/zf-content-negotiation/branches{/branch}", "tags_url": "https://api.github.com/repos/clickhere/zf-content-negotiation/tags", "blobs_url": "https://api.github.com/repos/clickhere/zf-content-negotiation/git/blobs{/sha}", "git_tags_url": "https://api.github.com/repos/clickhere/zf-content-negotiation/git/tags{/sha}", "git_refs_url": "https://api.github.com/repos/clickhere/zf-content-negotiation/git/refs{/sha}", "trees_url": "https://api.github.com/repos/clickhere/zf-content-negotiation/git/trees{/sha}", "statuses_url": "https://api.github.com/repos/clickhere/zf-content-negotiation/statuses/{sha}", "languages_url": "https://api.github.com/repos/clickhere/zf-content-negotiation/languages", "stargazers_url": "https://api.github.com/repos/clickhere/zf-content-negotiation/stargazers", "contributors_url": "https://api.github.com/repos/clickhere/zf-content-negotiation/contributors", "subscribers_url": "https://api.github.com/repos/clickhere/zf-content-negotiation/subscribers", "subscription_url": "https://api.github.com/repos/clickhere/zf-content-negotiation/subscription", "commits_url": "https://api.github.com/repos/clickhere/zf-content-negotiation/commits{/sha}", "git_commits_url": "https://api.github.com/repos/clickhere/zf-content-negotiation/git/commits{/sha}", "comments_url": "https://api.github.com/repos/clickhere/zf-content-negotiation/comments{/number}", "issue_comment_url": "https://api.github.com/repos/clickhere/zf-content-negotiation/issues/comments{/number}", "contents_url": "https://api.github.com/repos/clickhere/zf-content-negotiation/contents/{+path}", "compare_url": "https://api.github.com/repos/clickhere/zf-content-negotiation/compare/{base}...{head}", "merges_url": "https://api.github.com/repos/clickhere/zf-content-negotiation/merges", "archive_url": "https://api.github.com/repos/clickhere/zf-content-negotiation/{archive_format}{/ref}", "downloads_url": "https://api.github.com/repos/clickhere/zf-content-negotiation/downloads", "issues_url": "https://api.github.com/repos/clickhere/zf-content-negotiation/issues{/number}", "pulls_url": "https://api.github.com/repos/clickhere/zf-content-negotiation/pulls{/number}", "milestones_url": "https://api.github.com/repos/clickhere/zf-content-negotiation/milestones{/number}", "notifications_url": "https://api.github.com/repos/clickhere/zf-content-negotiation/notifications{?since,all,participating}", "labels_url": "https://api.github.com/repos/clickhere/zf-content-negotiation/labels{/name}", "releases_url": "https://api.github.com/repos/clickhere/zf-content-negotiation/releases{/id}", "deployments_url": "https://api.github.com/repos/clickhere/zf-content-negotiation/deployments", "created_at": "2016-01-07T23:33:07Z", "updated_at": "2016-01-07T23:33:44Z", "pushed_at": "2016-01-08T00:24:10Z", "git_url": "git://github.com/clickhere/zf-content-negotiation.git", "ssh_url": "git@github.com:clickhere/zf-content-negotiation.git", "clone_url": "https://github.com/clickhere/zf-content-negotiation.git", "svn_url": "https://github.com/clickhere/zf-content-negotiation", "homepage": null, "size": 195, "stargazers_count": 0, "watchers_count": 0, "language": "PHP", "has_issues": false, "has_projects": true, "has_downloads": true, "has_wiki": true, "has_pages": false, "forks_count": 0, "mirror_url": null, "archived": false, "disabled": false, "open_issues_count": 0, "license": {"key": "other", "name": "Other", "spdx_id": "NOASSERTION", "url": null, "node_id": "MDc6TGljZW5zZTA="}, "allow_forking": true, "is_template": false, "web_commit_signoff_required": false, "topics": [], "visibility": "public", "forks": 0, "open_issues": 0, "watchers": 0, "default_branch": "master", "permissions": {"admin": false, "maintain": false, "push": false, "triage": false, "pull": true}}, {"id": 68921399, "node_id": "MDEwOlJlcG9zaXRvcnk2ODkyMTM5OQ==", "name": "chl-php-build-test", "full_name": "clickhere/chl-php-build-test", "private": false, "owner": {"login": "clickhere", "id": 18863, "node_id": "MDEyOk9yZ2FuaXphdGlvbjE4ODYz", "avatar_url": "https://avatars.githubusercontent.com/u/18863?v=4", "gravatar_id": "", "url": "https://api.github.com/users/clickhere", "html_url": "https://github.com/clickhere", "followers_url": "https://api.github.com/users/clickhere/followers", "following_url": "https://api.github.com/users/clickhere/following{/other_user}", "gists_url": "https://api.github.com/users/clickhere/gists{/gist_id}", "starred_url": "https://api.github.com/users/clickhere/starred{/owner}{/repo}", "subscriptions_url": "https://api.github.com/users/clickhere/subscriptions", "organizations_url": "https://api.github.com/users/clickhere/orgs", "repos_url": "https://api.github.com/users/clickhere/repos", "events_url": "https://api.github.com/users/clickhere/events{/privacy}", "received_events_url": "https://api.github.com/users/clickhere/received_events", "type": "Organization", "site_admin": false}, "html_url": "https://github.com/clickhere/chl-php-build-test", "description": null, "fork": false, "url": "https://api.github.com/repos/clickhere/chl-php-build-test", "forks_url": "https://api.github.com/repos/clickhere/chl-php-build-test/forks", "keys_url": "https://api.github.com/repos/clickhere/chl-php-build-test/keys{/key_id}", "collaborators_url": "https://api.github.com/repos/clickhere/chl-php-build-test/collaborators{/collaborator}", "teams_url": "https://api.github.com/repos/clickhere/chl-php-build-test/teams", "hooks_url": "https://api.github.com/repos/clickhere/chl-php-build-test/hooks", "issue_events_url": "https://api.github.com/repos/clickhere/chl-php-build-test/issues/events{/number}", "events_url": "https://api.github.com/repos/clickhere/chl-php-build-test/events", "assignees_url": "https://api.github.com/repos/clickhere/chl-php-build-test/assignees{/user}", "branches_url": "https://api.github.com/repos/clickhere/chl-php-build-test/branches{/branch}", "tags_url": "https://api.github.com/repos/clickhere/chl-php-build-test/tags", "blobs_url": "https://api.github.com/repos/clickhere/chl-php-build-test/git/blobs{/sha}", "git_tags_url": "https://api.github.com/repos/clickhere/chl-php-build-test/git/tags{/sha}", "git_refs_url": "https://api.github.com/repos/clickhere/chl-php-build-test/git/refs{/sha}", "trees_url": "https://api.github.com/repos/clickhere/chl-php-build-test/git/trees{/sha}", "statuses_url": "https://api.github.com/repos/clickhere/chl-php-build-test/statuses/{sha}", "languages_url": "https://api.github.com/repos/clickhere/chl-php-build-test/languages", "stargazers_url": "https://api.github.com/repos/clickhere/chl-php-build-test/stargazers", "contributors_url": "https://api.github.com/repos/clickhere/chl-php-build-test/contributors", "subscribers_url": "https://api.github.com/repos/clickhere/chl-php-build-test/subscribers", "subscription_url": "https://api.github.com/repos/clickhere/chl-php-build-test/subscription", "commits_url": "https://api.github.com/repos/clickhere/chl-php-build-test/commits{/sha}", "git_commits_url": "https://api.github.com/repos/clickhere/chl-php-build-test/git/commits{/sha}", "comments_url": "https://api.github.com/repos/clickhere/chl-php-build-test/comments{/number}", "issue_comment_url": "https://api.github.com/repos/clickhere/chl-php-build-test/issues/comments{/number}", "contents_url": "https://api.github.com/repos/clickhere/chl-php-build-test/contents/{+path}", "compare_url": "https://api.github.com/repos/clickhere/chl-php-build-test/compare/{base}...{head}", "merges_url": "https://api.github.com/repos/clickhere/chl-php-build-test/merges", "archive_url": "https://api.github.com/repos/clickhere/chl-php-build-test/{archive_format}{/ref}", "downloads_url": "https://api.github.com/repos/clickhere/chl-php-build-test/downloads", "issues_url": "https://api.github.com/repos/clickhere/chl-php-build-test/issues{/number}", "pulls_url": "https://api.github.com/repos/clickhere/chl-php-build-test/pulls{/number}", "milestones_url": "https://api.github.com/repos/clickhere/chl-php-build-test/milestones{/number}", "notifications_url": "https://api.github.com/repos/clickhere/chl-php-build-test/notifications{?since,all,participating}", "labels_url": "https://api.github.com/repos/clickhere/chl-php-build-test/labels{/name}", "releases_url": "https://api.github.com/repos/clickhere/chl-php-build-test/releases{/id}", "deployments_url": "https://api.github.com/repos/clickhere/chl-php-build-test/deployments", "created_at": "2016-09-22T12:58:12Z", "updated_at": "2016-09-22T13:00:00Z", "pushed_at": "2016-09-26T18:16:31Z", "git_url": "git://github.com/clickhere/chl-php-build-test.git", "ssh_url": "git@github.com:clickhere/chl-php-build-test.git", "clone_url": "https://github.com/clickhere/chl-php-build-test.git", "svn_url": "https://github.com/clickhere/chl-php-build-test", "homepage": null, "size": 1, "stargazers_count": 0, "watchers_count": 0, "language": null, "has_issues": true, "has_projects": true, "has_downloads": true, "has_wiki": true, "has_pages": false, "forks_count": 1, "mirror_url": null, "archived": false, "disabled": false, "open_issues_count": 0, "license": null, "allow_forking": true, "is_template": false, "web_commit_signoff_required": false, "topics": [], "visibility": "public", "forks": 1, "open_issues": 0, "watchers": 0, "default_branch": "master", "permissions": {"admin": false, "maintain": false, "push": false, "triage": false, "pull": true}}, {"id": 89620534, "node_id": "MDEwOlJlcG9zaXRvcnk4OTYyMDUzNA==", "name": "capistrano-s3", "full_name": "clickhere/capistrano-s3", "private": false, "owner": {"login": "clickhere", "id": 18863, "node_id": "MDEyOk9yZ2FuaXphdGlvbjE4ODYz", "avatar_url": "https://avatars.githubusercontent.com/u/18863?v=4", "gravatar_id": "", "url": "https://api.github.com/users/clickhere", "html_url": "https://github.com/clickhere", "followers_url": "https://api.github.com/users/clickhere/followers", "following_url": "https://api.github.com/users/clickhere/following{/other_user}", "gists_url": "https://api.github.com/users/clickhere/gists{/gist_id}", "starred_url": "https://api.github.com/users/clickhere/starred{/owner}{/repo}", "subscriptions_url": "https://api.github.com/users/clickhere/subscriptions", "organizations_url": "https://api.github.com/users/clickhere/orgs", "repos_url": "https://api.github.com/users/clickhere/repos", "events_url": "https://api.github.com/users/clickhere/events{/privacy}", "received_events_url": "https://api.github.com/users/clickhere/received_events", "type": "Organization", "site_admin": false}, "html_url": "https://github.com/clickhere/capistrano-s3", "description": "Using Ruby and Capistrano, deploy a static website to an Amazon S3 website bucket.", "fork": true, "url": "https://api.github.com/repos/clickhere/capistrano-s3", "forks_url": "https://api.github.com/repos/clickhere/capistrano-s3/forks", "keys_url": "https://api.github.com/repos/clickhere/capistrano-s3/keys{/key_id}", "collaborators_url": "https://api.github.com/repos/clickhere/capistrano-s3/collaborators{/collaborator}", "teams_url": "https://api.github.com/repos/clickhere/capistrano-s3/teams", "hooks_url": "https://api.github.com/repos/clickhere/capistrano-s3/hooks", "issue_events_url": "https://api.github.com/repos/clickhere/capistrano-s3/issues/events{/number}", "events_url": "https://api.github.com/repos/clickhere/capistrano-s3/events", "assignees_url": "https://api.github.com/repos/clickhere/capistrano-s3/assignees{/user}", "branches_url": "https://api.github.com/repos/clickhere/capistrano-s3/branches{/branch}", "tags_url": "https://api.github.com/repos/clickhere/capistrano-s3/tags", "blobs_url": "https://api.github.com/repos/clickhere/capistrano-s3/git/blobs{/sha}", "git_tags_url": "https://api.github.com/repos/clickhere/capistrano-s3/git/tags{/sha}", "git_refs_url": "https://api.github.com/repos/clickhere/capistrano-s3/git/refs{/sha}", "trees_url": "https://api.github.com/repos/clickhere/capistrano-s3/git/trees{/sha}", "statuses_url": "https://api.github.com/repos/clickhere/capistrano-s3/statuses/{sha}", "languages_url": "https://api.github.com/repos/clickhere/capistrano-s3/languages", "stargazers_url": "https://api.github.com/repos/clickhere/capistrano-s3/stargazers", "contributors_url": "https://api.github.com/repos/clickhere/capistrano-s3/contributors", "subscribers_url": "https://api.github.com/repos/clickhere/capistrano-s3/subscribers", "subscription_url": "https://api.github.com/repos/clickhere/capistrano-s3/subscription", "commits_url": "https://api.github.com/repos/clickhere/capistrano-s3/commits{/sha}", "git_commits_url": "https://api.github.com/repos/clickhere/capistrano-s3/git/commits{/sha}", "comments_url": "https://api.github.com/repos/clickhere/capistrano-s3/comments{/number}", "issue_comment_url": "https://api.github.com/repos/clickhere/capistrano-s3/issues/comments{/number}", "contents_url": "https://api.github.com/repos/clickhere/capistrano-s3/contents/{+path}", "compare_url": "https://api.github.com/repos/clickhere/capistrano-s3/compare/{base}...{head}", "merges_url": "https://api.github.com/repos/clickhere/capistrano-s3/merges", "archive_url": "https://api.github.com/repos/clickhere/capistrano-s3/{archive_format}{/ref}", "downloads_url": "https://api.github.com/repos/clickhere/capistrano-s3/downloads", "issues_url": "https://api.github.com/repos/clickhere/capistrano-s3/issues{/number}", "pulls_url": "https://api.github.com/repos/clickhere/capistrano-s3/pulls{/number}", "milestones_url": "https://api.github.com/repos/clickhere/capistrano-s3/milestones{/number}", "notifications_url": "https://api.github.com/repos/clickhere/capistrano-s3/notifications{?since,all,participating}", "labels_url": "https://api.github.com/repos/clickhere/capistrano-s3/labels{/name}", "releases_url": "https://api.github.com/repos/clickhere/capistrano-s3/releases{/id}", "deployments_url": "https://api.github.com/repos/clickhere/capistrano-s3/deployments", "created_at": "2017-04-27T16:54:33Z", "updated_at": "2017-04-27T16:54:34Z", "pushed_at": "2017-06-07T21:24:24Z", "git_url": "git://github.com/clickhere/capistrano-s3.git", "ssh_url": "git@github.com:clickhere/capistrano-s3.git", "clone_url": "https://github.com/clickhere/capistrano-s3.git", "svn_url": "https://github.com/clickhere/capistrano-s3", "homepage": "https://rubygems.org/gems/capistrano-s3", "size": 132, "stargazers_count": 0, "watchers_count": 0, "language": "Ruby", "has_issues": false, "has_projects": true, "has_downloads": true, "has_wiki": true, "has_pages": false, "forks_count": 0, "mirror_url": null, "archived": false, "disabled": false, "open_issues_count": 0, "license": {"key": "other", "name": "Other", "spdx_id": "NOASSERTION", "url": null, "node_id": "MDc6TGljZW5zZTA="}, "allow_forking": true, "is_template": false, "web_commit_signoff_required": false, "topics": [], "visibility": "public", "forks": 0, "open_issues": 0, "watchers": 0, "default_branch": "master", "permissions": {"admin": false, "maintain": false, "push": false, "triage": false, "pull": true}}, {"id": 186666592, "node_id": "MDEwOlJlcG9zaXRvcnkxODY2NjY1OTI=", "name": "makerspace-demos", "full_name": "clickhere/makerspace-demos", "private": false, "owner": {"login": "clickhere", "id": 18863, "node_id": "MDEyOk9yZ2FuaXphdGlvbjE4ODYz", "avatar_url": "https://avatars.githubusercontent.com/u/18863?v=4", "gravatar_id": "", "url": "https://api.github.com/users/clickhere", "html_url": "https://github.com/clickhere", "followers_url": "https://api.github.com/users/clickhere/followers", "following_url": "https://api.github.com/users/clickhere/following{/other_user}", "gists_url": "https://api.github.com/users/clickhere/gists{/gist_id}", "starred_url": "https://api.github.com/users/clickhere/starred{/owner}{/repo}", "subscriptions_url": "https://api.github.com/users/clickhere/subscriptions", "organizations_url": "https://api.github.com/users/clickhere/orgs", "repos_url": "https://api.github.com/users/clickhere/repos", "events_url": "https://api.github.com/users/clickhere/events{/privacy}", "received_events_url": "https://api.github.com/users/clickhere/received_events", "type": "Organization", "site_admin": false}, "html_url": "https://github.com/clickhere/makerspace-demos", "description": "Makerspace Demos, May 2019", "fork": false, "url": "https://api.github.com/repos/clickhere/makerspace-demos", "forks_url": "https://api.github.com/repos/clickhere/makerspace-demos/forks", "keys_url": "https://api.github.com/repos/clickhere/makerspace-demos/keys{/key_id}", "collaborators_url": "https://api.github.com/repos/clickhere/makerspace-demos/collaborators{/collaborator}", "teams_url": "https://api.github.com/repos/clickhere/makerspace-demos/teams", "hooks_url": "https://api.github.com/repos/clickhere/makerspace-demos/hooks", "issue_events_url": "https://api.github.com/repos/clickhere/makerspace-demos/issues/events{/number}", "events_url": "https://api.github.com/repos/clickhere/makerspace-demos/events", "assignees_url": "https://api.github.com/repos/clickhere/makerspace-demos/assignees{/user}", "branches_url": "https://api.github.com/repos/clickhere/makerspace-demos/branches{/branch}", "tags_url": "https://api.github.com/repos/clickhere/makerspace-demos/tags", "blobs_url": "https://api.github.com/repos/clickhere/makerspace-demos/git/blobs{/sha}", "git_tags_url": "https://api.github.com/repos/clickhere/makerspace-demos/git/tags{/sha}", "git_refs_url": "https://api.github.com/repos/clickhere/makerspace-demos/git/refs{/sha}", "trees_url": "https://api.github.com/repos/clickhere/makerspace-demos/git/trees{/sha}", "statuses_url": "https://api.github.com/repos/clickhere/makerspace-demos/statuses/{sha}", "languages_url": "https://api.github.com/repos/clickhere/makerspace-demos/languages", "stargazers_url": "https://api.github.com/repos/clickhere/makerspace-demos/stargazers", "contributors_url": "https://api.github.com/repos/clickhere/makerspace-demos/contributors", "subscribers_url": "https://api.github.com/repos/clickhere/makerspace-demos/subscribers", "subscription_url": "https://api.github.com/repos/clickhere/makerspace-demos/subscription", "commits_url": "https://api.github.com/repos/clickhere/makerspace-demos/commits{/sha}", "git_commits_url": "https://api.github.com/repos/clickhere/makerspace-demos/git/commits{/sha}", "comments_url": "https://api.github.com/repos/clickhere/makerspace-demos/comments{/number}", "issue_comment_url": "https://api.github.com/repos/clickhere/makerspace-demos/issues/comments{/number}", "contents_url": "https://api.github.com/repos/clickhere/makerspace-demos/contents/{+path}", "compare_url": "https://api.github.com/repos/clickhere/makerspace-demos/compare/{base}...{head}", "merges_url": "https://api.github.com/repos/clickhere/makerspace-demos/merges", "archive_url": "https://api.github.com/repos/clickhere/makerspace-demos/{archive_format}{/ref}", "downloads_url": "https://api.github.com/repos/clickhere/makerspace-demos/downloads", "issues_url": "https://api.github.com/repos/clickhere/makerspace-demos/issues{/number}", "pulls_url": "https://api.github.com/repos/clickhere/makerspace-demos/pulls{/number}", "milestones_url": "https://api.github.com/repos/clickhere/makerspace-demos/milestones{/number}", "notifications_url": "https://api.github.com/repos/clickhere/makerspace-demos/notifications{?since,all,participating}", "labels_url": "https://api.github.com/repos/clickhere/makerspace-demos/labels{/name}", "releases_url": "https://api.github.com/repos/clickhere/makerspace-demos/releases{/id}", "deployments_url": "https://api.github.com/repos/clickhere/makerspace-demos/deployments", "created_at": "2019-05-14T17:10:29Z", "updated_at": "2021-01-21T21:10:55Z", "pushed_at": "2021-01-21T04:53:55Z", "git_url": "git://github.com/clickhere/makerspace-demos.git", "ssh_url": "git@github.com:clickhere/makerspace-demos.git", "clone_url": "https://github.com/clickhere/makerspace-demos.git", "svn_url": "https://github.com/clickhere/makerspace-demos", "homepage": "https://clickhere.github.io/makerspace-demos", "size": 1878, "stargazers_count": 0, "watchers_count": 0, "language": "JavaScript", "has_issues": true, "has_projects": true, "has_downloads": true, "has_wiki": true, "has_pages": true, "forks_count": 0, "mirror_url": null, "archived": true, "disabled": false, "open_issues_count": 10, "license": null, "allow_forking": true, "is_template": false, "web_commit_signoff_required": false, "topics": [], "visibility": "public", "forks": 0, "open_issues": 10, "watchers": 0, "default_branch": "master", "permissions": {"admin": false, "maintain": false, "push": false, "triage": false, "pull": true}}, {"id": 491995141, "node_id": "R_kgDOHVNABQ", "name": "chl-titan-blueprint", "full_name": "clickhere/chl-titan-blueprint", "private": false, "owner": {"login": "clickhere", "id": 18863, "node_id": "MDEyOk9yZ2FuaXphdGlvbjE4ODYz", "avatar_url": "https://avatars.githubusercontent.com/u/18863?v=4", "gravatar_id": "", "url": "https://api.github.com/users/clickhere", "html_url": "https://github.com/clickhere", "followers_url": "https://api.github.com/users/clickhere/followers", "following_url": "https://api.github.com/users/clickhere/following{/other_user}", "gists_url": "https://api.github.com/users/clickhere/gists{/gist_id}", "starred_url": "https://api.github.com/users/clickhere/starred{/owner}{/repo}", "subscriptions_url": "https://api.github.com/users/clickhere/subscriptions", "organizations_url": "https://api.github.com/users/clickhere/orgs", "repos_url": "https://api.github.com/users/clickhere/repos", "events_url": "https://api.github.com/users/clickhere/events{/privacy}", "received_events_url": "https://api.github.com/users/clickhere/received_events", "type": "Organization", "site_admin": false}, "html_url": "https://github.com/clickhere/chl-titan-blueprint", "description": "WPE Titan Blueprint", "fork": false, "url": "https://api.github.com/repos/clickhere/chl-titan-blueprint", "forks_url": "https://api.github.com/repos/clickhere/chl-titan-blueprint/forks", "keys_url": "https://api.github.com/repos/clickhere/chl-titan-blueprint/keys{/key_id}", "collaborators_url": "https://api.github.com/repos/clickhere/chl-titan-blueprint/collaborators{/collaborator}", "teams_url": "https://api.github.com/repos/clickhere/chl-titan-blueprint/teams", "hooks_url": "https://api.github.com/repos/clickhere/chl-titan-blueprint/hooks", "issue_events_url": "https://api.github.com/repos/clickhere/chl-titan-blueprint/issues/events{/number}", "events_url": "https://api.github.com/repos/clickhere/chl-titan-blueprint/events", "assignees_url": "https://api.github.com/repos/clickhere/chl-titan-blueprint/assignees{/user}", "branches_url": "https://api.github.com/repos/clickhere/chl-titan-blueprint/branches{/branch}", "tags_url": "https://api.github.com/repos/clickhere/chl-titan-blueprint/tags", "blobs_url": "https://api.github.com/repos/clickhere/chl-titan-blueprint/git/blobs{/sha}", "git_tags_url": "https://api.github.com/repos/clickhere/chl-titan-blueprint/git/tags{/sha}", "git_refs_url": "https://api.github.com/repos/clickhere/chl-titan-blueprint/git/refs{/sha}", "trees_url": "https://api.github.com/repos/clickhere/chl-titan-blueprint/git/trees{/sha}", "statuses_url": "https://api.github.com/repos/clickhere/chl-titan-blueprint/statuses/{sha}", "languages_url": "https://api.github.com/repos/clickhere/chl-titan-blueprint/languages", "stargazers_url": "https://api.github.com/repos/clickhere/chl-titan-blueprint/stargazers", "contributors_url": "https://api.github.com/repos/clickhere/chl-titan-blueprint/contributors", "subscribers_url": "https://api.github.com/repos/clickhere/chl-titan-blueprint/subscribers", "subscription_url": "https://api.github.com/repos/clickhere/chl-titan-blueprint/subscription", "commits_url": "https://api.github.com/repos/clickhere/chl-titan-blueprint/commits{/sha}", "git_commits_url": "https://api.github.com/repos/clickhere/chl-titan-blueprint/git/commits{/sha}", "comments_url": "https://api.github.com/repos/clickhere/chl-titan-blueprint/comments{/number}", "issue_comment_url": "https://api.github.com/repos/clickhere/chl-titan-blueprint/issues/comments{/number}", "contents_url": "https://api.github.com/repos/clickhere/chl-titan-blueprint/contents/{+path}", "compare_url": "https://api.github.com/repos/clickhere/chl-titan-blueprint/compare/{base}...{head}", "merges_url": "https://api.github.com/repos/clickhere/chl-titan-blueprint/merges", "archive_url": "https://api.github.com/repos/clickhere/chl-titan-blueprint/{archive_format}{/ref}", "downloads_url": "https://api.github.com/repos/clickhere/chl-titan-blueprint/downloads", "issues_url": "https://api.github.com/repos/clickhere/chl-titan-blueprint/issues{/number}", "pulls_url": "https://api.github.com/repos/clickhere/chl-titan-blueprint/pulls{/number}", "milestones_url": "https://api.github.com/repos/clickhere/chl-titan-blueprint/milestones{/number}", "notifications_url": "https://api.github.com/repos/clickhere/chl-titan-blueprint/notifications{?since,all,participating}", "labels_url": "https://api.github.com/repos/clickhere/chl-titan-blueprint/labels{/name}", "releases_url": "https://api.github.com/repos/clickhere/chl-titan-blueprint/releases{/id}", "deployments_url": "https://api.github.com/repos/clickhere/chl-titan-blueprint/deployments", "created_at": "2022-05-13T18:03:35Z", "updated_at": "2022-08-30T13:59:29Z", "pushed_at": "2022-09-14T22:26:25Z", "git_url": "git://github.com/clickhere/chl-titan-blueprint.git", "ssh_url": "git@github.com:clickhere/chl-titan-blueprint.git", "clone_url": "https://github.com/clickhere/chl-titan-blueprint.git", "svn_url": "https://github.com/clickhere/chl-titan-blueprint", "homepage": null, "size": 914, "stargazers_count": 0, "watchers_count": 0, "language": null, "has_issues": true, "has_projects": true, "has_downloads": true, "has_wiki": true, "has_pages": false, "forks_count": 0, "mirror_url": null, "archived": false, "disabled": false, "open_issues_count": 0, "license": null, "allow_forking": true, "is_template": false, "web_commit_signoff_required": false, "topics": [], "visibility": "public", "forks": 0, "open_issues": 0, "watchers": 0, "default_branch": "tmp", "permissions": {"admin": false, "maintain": false, "push": false, "triage": false, "pull": true}}, {"id": 529420564, "node_id": "R_kgDOH45RFA", "name": "atlas-blueprint-blog", "full_name": "clickhere/atlas-blueprint-blog", "private": false, "owner": {"login": "clickhere", "id": 18863, "node_id": "MDEyOk9yZ2FuaXphdGlvbjE4ODYz", "avatar_url": "https://avatars.githubusercontent.com/u/18863?v=4", "gravatar_id": "", "url": "https://api.github.com/users/clickhere", "html_url": "https://github.com/clickhere", "followers_url": "https://api.github.com/users/clickhere/followers", "following_url": "https://api.github.com/users/clickhere/following{/other_user}", "gists_url": "https://api.github.com/users/clickhere/gists{/gist_id}", "starred_url": "https://api.github.com/users/clickhere/starred{/owner}{/repo}", "subscriptions_url": "https://api.github.com/users/clickhere/subscriptions", "organizations_url": "https://api.github.com/users/clickhere/orgs", "repos_url": "https://api.github.com/users/clickhere/repos", "events_url": "https://api.github.com/users/clickhere/events{/privacy}", "received_events_url": "https://api.github.com/users/clickhere/received_events", "type": "Organization", "site_admin": false}, "html_url": "https://github.com/clickhere/atlas-blueprint-blog", "description": null, "fork": false, "url": "https://api.github.com/repos/clickhere/atlas-blueprint-blog", "forks_url": "https://api.github.com/repos/clickhere/atlas-blueprint-blog/forks", "keys_url": "https://api.github.com/repos/clickhere/atlas-blueprint-blog/keys{/key_id}", "collaborators_url": "https://api.github.com/repos/clickhere/atlas-blueprint-blog/collaborators{/collaborator}", "teams_url": "https://api.github.com/repos/clickhere/atlas-blueprint-blog/teams", "hooks_url": "https://api.github.com/repos/clickhere/atlas-blueprint-blog/hooks", "issue_events_url": "https://api.github.com/repos/clickhere/atlas-blueprint-blog/issues/events{/number}", "events_url": "https://api.github.com/repos/clickhere/atlas-blueprint-blog/events", "assignees_url": "https://api.github.com/repos/clickhere/atlas-blueprint-blog/assignees{/user}", "branches_url": "https://api.github.com/repos/clickhere/atlas-blueprint-blog/branches{/branch}", "tags_url": "https://api.github.com/repos/clickhere/atlas-blueprint-blog/tags", "blobs_url": "https://api.github.com/repos/clickhere/atlas-blueprint-blog/git/blobs{/sha}", "git_tags_url": "https://api.github.com/repos/clickhere/atlas-blueprint-blog/git/tags{/sha}", "git_refs_url": "https://api.github.com/repos/clickhere/atlas-blueprint-blog/git/refs{/sha}", "trees_url": "https://api.github.com/repos/clickhere/atlas-blueprint-blog/git/trees{/sha}", "statuses_url": "https://api.github.com/repos/clickhere/atlas-blueprint-blog/statuses/{sha}", "languages_url": "https://api.github.com/repos/clickhere/atlas-blueprint-blog/languages", "stargazers_url": "https://api.github.com/repos/clickhere/atlas-blueprint-blog/stargazers", "contributors_url": "https://api.github.com/repos/clickhere/atlas-blueprint-blog/contributors", "subscribers_url": "https://api.github.com/repos/clickhere/atlas-blueprint-blog/subscribers", "subscription_url": "https://api.github.com/repos/clickhere/atlas-blueprint-blog/subscription", "commits_url": "https://api.github.com/repos/clickhere/atlas-blueprint-blog/commits{/sha}", "git_commits_url": "https://api.github.com/repos/clickhere/atlas-blueprint-blog/git/commits{/sha}", "comments_url": "https://api.github.com/repos/clickhere/atlas-blueprint-blog/comments{/number}", "issue_comment_url": "https://api.github.com/repos/clickhere/atlas-blueprint-blog/issues/comments{/number}", "contents_url": "https://api.github.com/repos/clickhere/atlas-blueprint-blog/contents/{+path}", "compare_url": "https://api.github.com/repos/clickhere/atlas-blueprint-blog/compare/{base}...{head}", "merges_url": "https://api.github.com/repos/clickhere/atlas-blueprint-blog/merges", "archive_url": "https://api.github.com/repos/clickhere/atlas-blueprint-blog/{archive_format}{/ref}", "downloads_url": "https://api.github.com/repos/clickhere/atlas-blueprint-blog/downloads", "issues_url": "https://api.github.com/repos/clickhere/atlas-blueprint-blog/issues{/number}", "pulls_url": "https://api.github.com/repos/clickhere/atlas-blueprint-blog/pulls{/number}", "milestones_url": "https://api.github.com/repos/clickhere/atlas-blueprint-blog/milestones{/number}", "notifications_url": "https://api.github.com/repos/clickhere/atlas-blueprint-blog/notifications{?since,all,participating}", "labels_url": "https://api.github.com/repos/clickhere/atlas-blueprint-blog/labels{/name}", "releases_url": "https://api.github.com/repos/clickhere/atlas-blueprint-blog/releases{/id}", "deployments_url": "https://api.github.com/repos/clickhere/atlas-blueprint-blog/deployments", "created_at": "2022-08-26T22:28:11Z", "updated_at": "2022-08-26T22:28:21Z", "pushed_at": "2022-08-26T22:28:17Z", "git_url": "git://github.com/clickhere/atlas-blueprint-blog.git", "ssh_url": "git@github.com:clickhere/atlas-blueprint-blog.git", "clone_url": "https://github.com/clickhere/atlas-blueprint-blog.git", "svn_url": "https://github.com/clickhere/atlas-blueprint-blog", "homepage": null, "size": 3599, "stargazers_count": 0, "watchers_count": 0, "language": "JavaScript", "has_issues": true, "has_projects": true, "has_downloads": true, "has_wiki": true, "has_pages": false, "forks_count": 0, "mirror_url": null, "archived": false, "disabled": false, "open_issues_count": 0, "license": null, "allow_forking": true, "is_template": false, "web_commit_signoff_required": false, "topics": [], "visibility": "public", "forks": 0, "open_issues": 0, "watchers": 0, "default_branch": "main", "permissions": {"admin": false, "maintain": false, "push": false, "triage": false, "pull": true}}]